notebook_frontend/__init__.py
notebook_frontend/py.typed
notebook_frontend/static/100.76dcd4324b7a28791d02.js
notebook_frontend/static/100.76dcd4324b7a28791d02.js.map
notebook_frontend/static/1053.e198cdda6c9dcfc5953a.js
notebook_frontend/static/1053.e198cdda6c9dcfc5953a.js.map
notebook_frontend/static/1088.f26c568e858d1f160276.js
notebook_frontend/static/1088.f26c568e858d1f160276.js.map
notebook_frontend/static/1091.2d246ab9d25cc7159b01.js
notebook_frontend/static/1091.2d246ab9d25cc7159b01.js.map
notebook_frontend/static/1122.16363dcd990a9685123e.js
notebook_frontend/static/1122.16363dcd990a9685123e.js.map
notebook_frontend/static/114.3735fbb3fc442d926d2b.js
notebook_frontend/static/114.3735fbb3fc442d926d2b.js.map
notebook_frontend/static/1169.5a41d184b1a9eb054672.js
notebook_frontend/static/1225.a84f9ad316be9c1538e1.js
notebook_frontend/static/1225.a84f9ad316be9c1538e1.js.map
notebook_frontend/static/131.729c28b8323daf822cbe.js
notebook_frontend/static/131.729c28b8323daf822cbe.js.map
notebook_frontend/static/1418.5913bb08784c217a1f0b.js
notebook_frontend/static/1418.5913bb08784c217a1f0b.js.map
notebook_frontend/static/1468.38f64176ff236023d384.js
notebook_frontend/static/1468.38f64176ff236023d384.js.map
notebook_frontend/static/1542.8f0b79431f7af2f43f1e.js
notebook_frontend/static/1542.8f0b79431f7af2f43f1e.js.map
notebook_frontend/static/1558.d1ebe7cb088451b0d7de.js
notebook_frontend/static/1558.d1ebe7cb088451b0d7de.js.map
notebook_frontend/static/1584.f1f06903491cfdeed6dc.js
notebook_frontend/static/1584.f1f06903491cfdeed6dc.js.map
notebook_frontend/static/1601.4154c4f9ed460feae33b.js
notebook_frontend/static/1601.4154c4f9ed460feae33b.js.map
notebook_frontend/static/1602.1f9163a55b87ec440fc5.js
notebook_frontend/static/1602.1f9163a55b87ec440fc5.js.map
notebook_frontend/static/1608.349cbefc33c43cfe5d1f.js
notebook_frontend/static/1608.349cbefc33c43cfe5d1f.js.map
notebook_frontend/static/1616.ee161d92c1ef1d77afcc.js
notebook_frontend-7.5.3.dist-info/METADATA
notebook_frontend-7.5.3.dist-info/WHEEL
notebook_frontend-7.5.3.dist-info/licenses/LICENSE
notebook_frontend-7.5.3.dist-info/RECORD
