Metadata-Version: 2.4
Name: notebook-frontend
Version: 7.5.3
Summary: A Python package distributing Notebook's static assets
Project-URL: Source, https://github.com/davidbrochart/notebook-frontend
Author-email: David Brochart <david.brochart@gmail.com>
License: MIT License
License-File: LICENSE
Classifier: Development Status :: 4 - Beta
Classifier: Intended Audience :: Developers
Classifier: License :: OSI Approved :: BSD License
Classifier: Programming Language :: Python
Classifier: Programming Language :: Python :: 3
Classifier: Programming Language :: Python :: 3.10
Classifier: Programming Language :: Python :: 3.11
Classifier: Programming Language :: Python :: 3.12
Classifier: Programming Language :: Python :: 3.13
Classifier: Programming Language :: Python :: 3.14
Classifier: Typing :: Typed
Requires-Dist: jupyterlab-js<4.5.4,>=4.5.3
